LICENSE
MANIFEST.in
README.md
pyproject.toml
setup.cfg
setup.py
src/hhcristian.egg-info/PKG-INFO
src/hhcristian.egg-info/SOURCES.txt
src/hhcristian.egg-info/dependency_links.txt
src/hhcristian.egg-info/entry_points.txt
src/hhcristian.egg-info/requires.txt
src/hhcristian.egg-info/top_level.txt
src/imppkg/__init__.py
src/imppkg/data.json
src/imppkg/harmonic_mean.c
src/imppkg/harmonic_mean.pyx
src/imppkg/harmony.py
src/imppkg/py.typed
src/pubpypack_harmony_dane_hillard.egg-info/PKG-INFO
src/pubpypack_harmony_dane_hillard.egg-info/SOURCES.txt
src/pubpypack_harmony_dane_hillard.egg-info/dependency_links.txt
src/pubpypack_harmony_dane_hillard.egg-info/entry_points.txt
src/pubpypack_harmony_dane_hillard.egg-info/requires.txt
src/pubpypack_harmony_dane_hillard.egg-info/top_level.txt
test/test_harmonic_mean.py