Metadata-Version: 2.1
Name: hhcristian
Version: 0.0.2
Summary: This package does amazing things.
Home-page: https://github.com/daneah/publishing-python-packages
Author: CBandea
Author-email: "Dane Hillard" <github@danehillard.com>
License: MIT
Classifier: License :: OSI Approved :: MIT License
Requires-Python: >=3.9
License-File: LICENSE
Requires-Dist: termcolor<2,>=1.1.0
